LICENSE
README.md
setup.cfg
setup.py
argexec/__init__.py
argexec/_decorator.py
argexec/_docstring.py
argexec.egg-info/PKG-INFO
argexec.egg-info/SOURCES.txt
argexec.egg-info/dependency_links.txt
argexec.egg-info/requires.txt
argexec.egg-info/top_level.txt
argexec/types/__init__.py
argexec/types/_default.py
argexec/types/_log_level.py
tests/__init__.py