Metadata-Version: 2.1
Name: argexec
Version: 1.0.2
Summary: Expose your Python functions to the command line with one easy step!
Home-page: https://github.com/XevoInc/argexec
Author: Ryan Rowe
Author-email: rrowe@xevo.com
License: Apache License, Version 2.0
Platform: UNKNOWN
Classifier: Development Status :: 4 - Beta
Classifier: Intended Audience :: Developers
Classifier: License :: OSI Approved :: Apache Software License
Classifier: Programming Language :: Python
Classifier: Programming Language :: Python :: 3.7
Classifier: Programming Language :: Python :: 3.8
Classifier: Topic :: Utilities
Classifier: Typing :: Typed
Provides-Extra: dev
